sial/__init__.py
sial/crosser.py
sial/inferer.py
sial/utils.py
sial_pkg-0.0.8.dist-info/LICENSE
sial_pkg-0.0.8.dist-info/METADATA
sial_pkg-0.0.8.dist-info/WHEEL
sial_pkg-0.0.8.dist-info/top_level.txt
sial_pkg-0.0.8.dist-info/RECORD
