Metadata-Version: 2.1
Name: sial-pkg
Version: 0.0.8
Summary: Statistical Inference After Learning
Author-email: Po-Hsien Huang <psyphh@nccu.edu.tw>
Classifier: Programming Language :: Python :: 3
Classifier: License :: OSI Approved :: MIT License
Classifier: Operating System :: OS Independent
Requires-Python: >=3.9
License-File: LICENSE
Requires-Dist: scikit-learn >=1.5.0
Requires-Dist: pandas >=2.0.3
